hotkey/__init__.py
hotkey/hotkey.py
tests/__init__.py
hotkey-0.1.0.dist-info/LICENSE
hotkey-0.1.0.dist-info/METADATA
hotkey-0.1.0.dist-info/WHEEL
hotkey-0.1.0.dist-info/top_level.txt
hotkey-0.1.0.dist-info/RECORD
