Metadata-Version: 2.1
Name: hotkey
Version: 0.1.0
Summary: This is a package for hoykeys
Home-page: https://github.com/Bilski311/hotkey
Author: Dominik Bilski
Author-email: dominik.bilski42@gmail.com
Classifier: Programming Language :: Python :: 3
Classifier: License :: OSI Approved :: MIT License
Classifier: Operating System :: OS Independent
Requires-Python: >=3.12
License-File: LICENSE
